epypes/__init__.py
epypes/cli.py
epypes/codegen.py
epypes/commons.py
epypes/compgraph.py
epypes/graph.py
epypes/loop.py
epypes/node.py
epypes/payload.py
epypes/pipeline.py
epypes/queue.py
epypes/reactivevision.py
epypes/util.py
epypes/zeromq.py
epypes/protobuf/__init__.py
epypes/protobuf/attributes_pb2.py
epypes/protobuf/event_pb2.py
epypes/protobuf/image_pb2.py
epypes/protobuf/imagepair_pb2.py
epypes/protobuf/justbytes_pb2.py
epypes/protobuf/pbprocess.py
epypes/protobuf/pbtypes.py
epypes/protobuf/timestamp_pb2.py
epypes-0.1.1.dist-info/LICENSE.txt
epypes-0.1.1.dist-info/METADATA
epypes-0.1.1.dist-info/WHEEL
epypes-0.1.1.dist-info/top_level.txt
epypes-0.1.1.dist-info/RECORD
