Metadata-Version: 2.1
Name: epypes
Version: 0.1.1
Summary: UNKNOWN
Home-page: UNKNOWN
Author: Oleksandr Semeniuta
Author-email: oleksandr.semeniuta@gmail.com
License: BSD license
Platform: UNKNOWN
Requires-Dist: pyzmq
Requires-Dist: protobuf
Requires-Dist: networkx (>=2.0)
